fastdata/None.py
fastdata/__init__.py
fastdata/_nbdev.py
fastdata/core.py
fastdata/integrations.py
fastdata-0.0.22.dist-info/LICENSE
fastdata-0.0.22.dist-info/METADATA
fastdata-0.0.22.dist-info/WHEEL
fastdata-0.0.22.dist-info/entry_points.txt
fastdata-0.0.22.dist-info/top_level.txt
fastdata-0.0.22.dist-info/RECORD
