Metadata-Version: 2.1
Name: fastdata
Version: 0.0.22
Summary: A library to accelerate data-science productivity with Pandas. Best used with the eigendata jupyterlab extension.
Home-page: https://github.com/molinsp/fastdata/tree/master/
Author: Pere Molins
Author-email: molinsp@gmail.com
License: Apache Software License 2.0
Keywords: data analysis,data science
Platform: UNKNOWN
Classifier: Development Status :: 3 - Alpha
Classifier: Intended Audience :: Developers
Classifier: License :: OSI Approved :: Apache Software License
Classifier: Natural Language :: English
Classifier: Programming Language :: Python :: 3.6
Classifier: Programming Language :: Python :: 3.7
Classifier: Programming Language :: Python :: 3.8
Requires-Python: >=3.6
License-File: LICENSE
Requires-Dist: pandas (>=1.0.0)
Requires-Dist: numpy (>=1.0.0)
Requires-Dist: fastcore (>=1.1.0)
Requires-Dist: jmespath (>=0.10.0)
Requires-Dist: gspread (>=3.6.0)
Requires-Dist: gspread-pandas (>=2.2.3)
Requires-Dist: pyairtable (>=1.0.0)
